{
  "group": "初中（五•四学制）_艺术_音乐",
  "count": 13,
  "books": [
    {
      "id": "69ac1a5a-770f-40bc-b941-fa98d0a0541b",
      "title": "（根据2022年版课程标准修订）义务教育教科书（五•四学制）•艺术•音乐（简谱）六年级上册",
      "path": "初中（五•四学制） > 艺术·音乐 > 鲁教版 > 六年级 > 上册",
      "url": "https://basic.smartedu.cn/tchMaterial/detail?contentType=assets_document&contentId=69ac1a5a-770f-40bc-b941-fa98d0a0541b&catalogType=tchMaterial&subCatalog=tchMaterial"
    },
    {
      "id": "4f89ce26-e1c9-45f0-8a14-010c202f98b8",
      "title": "（根据2022年版课程标准修订）义务教育教科书（五•四学制）·音乐六年级下册",
      "path": "初中（五•四学制） > 艺术·音乐 > 鲁教版 > 六年级 > 下册",
      "url": "https://basic.smartedu.cn/tchMaterial/detail?contentType=assets_document&contentId=4f89ce26-e1c9-45f0-8a14-010c202f98b8&catalogType=tchMaterial&subCatalog=tchMaterial"
    },
    {
      "id": "7ea88531-ad4d-4e41-9820-f83f49f04f04",
      "title": "（根据2022年版课程标准修订）义务教育教科书（五•四学制）•艺术•音乐（简谱）七年级上册",
      "path": "初中（五•四学制） > 艺术·音乐 > 鲁教版 > 七年级 > 上册",
      "url": "https://basic.smartedu.cn/tchMaterial/detail?contentType=assets_document&contentId=7ea88531-ad4d-4e41-9820-f83f49f04f04&catalogType=tchMaterial&subCatalog=tchMaterial"
    },
    {
      "id": "5bd52c33-b0c6-4498-a767-2216477b17eb",
      "title": "义务教育教科书（五•四学制）·音乐七年级下册",
      "path": "初中（五•四学制） > 艺术·音乐 > 鲁教版 > 七年级 > 下册",
      "url": "https://basic.smartedu.cn/tchMaterial/detail?contentType=assets_document&contentId=5bd52c33-b0c6-4498-a767-2216477b17eb&catalogType=tchMaterial&subCatalog=tchMaterial"
    },
    {
      "id": "26790587-77c3-4aa6-99e8-6b617efdbe4e",
      "title": "义务教育教科书（五•四学制）·音乐八年级上册",
      "path": "初中（五•四学制） > 艺术·音乐 > 鲁教版 > 八年级 > 上册",
      "url": "https://basic.smartedu.cn/tchMaterial/detail?contentType=assets_document&contentId=26790587-77c3-4aa6-99e8-6b617efdbe4e&catalogType=tchMaterial&subCatalog=tchMaterial"
    },
    {
      "id": "e23f7d60-52f3-4644-8c7a-78eac7654023",
      "title": "义务教育教科书（五•四学制）·音乐八年级下册",
      "path": "初中（五•四学制） > 艺术·音乐 > 鲁教版 > 八年级 > 下册",
      "url": "https://basic.smartedu.cn/tchMaterial/detail?contentType=assets_document&contentId=e23f7d60-52f3-4644-8c7a-78eac7654023&catalogType=tchMaterial&subCatalog=tchMaterial"
    },
    {
      "id": "b3c3bd9e-d10f-4d20-826c-2a3e6ea113c0",
      "title": "义务教育教科书（五•四学制）·音乐九年级上册",
      "path": "初中（五•四学制） > 艺术·音乐 > 鲁教版 > 九年级 > 上册",
      "url": "https://basic.smartedu.cn/tchMaterial/detail?contentType=assets_document&contentId=b3c3bd9e-d10f-4d20-826c-2a3e6ea113c0&catalogType=tchMaterial&subCatalog=tchMaterial"
    },
    {
      "id": "11933a47-43ef-47ae-a584-ba78a64b2490",
      "title": "义务教育教科书（五•四学制）·音乐九年级下册",
      "path": "初中（五•四学制） > 艺术·音乐 > 鲁教版 > 九年级 > 下册",
      "url": "https://basic.smartedu.cn/tchMaterial/detail?contentType=assets_document&contentId=11933a47-43ef-47ae-a584-ba78a64b2490&catalogType=tchMaterial&subCatalog=tchMaterial"
    },
    {
      "id": "75213d2a-f34c-f97c-6749-00f5ab7c649b",
      "title": "（根据2022年版课程标准修订）义务教育教科书（五•四学制）•音乐七年级上册",
      "path": "初中（五•四学制） > 艺术·音乐 > 沪音版 > 七年级 > 上册",
      "url": "https://basic.smartedu.cn/tchMaterial/detail?contentType=assets_document&contentId=75213d2a-f34c-f97c-6749-00f5ab7c649b&catalogType=tchMaterial&subCatalog=tchMaterial"
    },
    {
      "id": "e19e0540-a5ab-d85a-6397-aa652d8b1a8a",
      "title": "（根据2022年版课程标准修订）义务教育教科书（五•四学制）•音乐六年级上册",
      "path": "初中（五•四学制） > 艺术·音乐 > 沪音版 > 六年级 > 上册",
      "url": "https://basic.smartedu.cn/tchMaterial/detail?contentType=assets_document&contentId=e19e0540-a5ab-d85a-6397-aa652d8b1a8a&catalogType=tchMaterial&subCatalog=tchMaterial"
    },
    {
      "id": "ad1beb95-bb2e-7734-ae4f-fa4efc87492f",
      "title": "（根据2022年版课程标准修订）义务教育教科书（五•四学制）•音乐六年级下册",
      "path": "初中（五•四学制） > 艺术·音乐 > 沪音版 > 六年级 > 下册",
      "url": "https://basic.smartedu.cn/tchMaterial/detail?contentType=assets_document&contentId=ad1beb95-bb2e-7734-ae4f-fa4efc87492f&catalogType=tchMaterial&subCatalog=tchMaterial"
    },
    {
      "id": "44142530-6cd1-ccf4-4435-dcae81a4b0ae",
      "title": "（根据2022年版课程标准修订）义务教育教科书（五•四学制）•音乐七年级下册",
      "path": "初中（五•四学制） > 艺术·音乐 > 沪音版 > 七年级 > 下册",
      "url": "https://basic.smartedu.cn/tchMaterial/detail?contentType=assets_document&contentId=44142530-6cd1-ccf4-4435-dcae81a4b0ae&catalogType=tchMaterial&subCatalog=tchMaterial"
    },
    {
      "id": "bb70cdcf-ae95-4dfb-5fe7-59d983cbb417",
      "title": "（根据2022年版课程标准修订）义务教育教科书（五•四学制）•音乐八年级上册",
      "path": "初中（五•四学制） > 艺术·音乐 > 沪音版 > 八年级 > 上册",
      "url": "https://basic.smartedu.cn/tchMaterial/detail?contentType=assets_document&contentId=bb70cdcf-ae95-4dfb-5fe7-59d983cbb417&catalogType=tchMaterial&subCatalog=tchMaterial"
    }
  ]
}